{
  "InputCollect": {
    "date_var": ["date"],
    "dayInterval": [7],
    "intervalType": ["week"],
    "dep_var": ["sales"],
    "dep_var_type": ["revenue"],
    "prophet_vars": ["trend", "season", "holiday"],
    "prophet_signs": ["default", "default", "default"],
    "prophet_country": ["IN"],
    "context_vars": ["cpi", "gdp_growth", "festival", "trade_spend"],
    "context_signs": ["default", "default", "default", "default"],
    "paid_media_vars": ["tv", "youtube", "facebook", "instagram", "print_media", "radio"],
    "paid_media_signs": ["positive", "positive", "positive", "positive", "positive", "positive"],
    "paid_media_spends": ["tv", "youtube", "facebook", "instagram", "print_media", "radio"],
    "paid_media_selected": ["tv", "youtube", "facebook", "instagram", "print_media", "radio"],
    "paid_media_total": [27408373340.738609],
    "exposure_vars": [],
    "all_media": ["tv", "youtube", "facebook", "instagram", "print_media", "radio"],
    "all_ind_vars": ["trend", "season", "holiday", "cpi", "gdp_growth", "festival", "trade_spend", "tv", "youtube", "facebook", "instagram", "print_media", "radio"],
    "unused_vars": ["rainfall"],
    "window_start": ["2022-07-04"],
    "rollingWindowStartWhich": [1],
    "window_end": ["2025-06-23"],
    "rollingWindowEndWhich": [156],
    "rollingWindowLength": [156],
    "totalObservations": [156],
    "refreshAddedStart": ["2022-07-04"],
    "adstock": ["geometric"],
    "hyperparameters": {
      "tv_alphas": [0.5, 3],
      "tv_gammas": [0.3, 1],
      "tv_thetas": [0.5, 0.85],
      "youtube_alphas": [0.5, 3],
      "youtube_gammas": [0.3, 1],
      "youtube_thetas": [0.2, 0.55],
      "facebook_alphas": [0.5, 3],
      "facebook_gammas": [0.3, 1],
      "facebook_thetas": [0.15, 0.5],
      "instagram_alphas": [0.5, 3],
      "instagram_gammas": [0.3, 1],
      "instagram_thetas": [0.1, 0.45],
      "print_media_alphas": [0.5, 3],
      "print_media_gammas": [0.3, 1],
      "print_media_thetas": [0.3, 0.65],
      "radio_alphas": [0.5, 3],
      "radio_gammas": [0.3, 1],
      "radio_thetas": [0.25, 0.6],
      "train_size": [0.5, 0.8]
    },
    "calibration_input": {},
    "custom_params": [],
    "version": ["Robyn (stable) v3.12.1 [R-4.5.3]"]
  },
  "ModelsCollect": {
    "ts_validation": [false],
    "train_timestamp": ["2026-04-12 19:46:23"],
    "export_timestamp": ["2026-04-12 19:50:08"],
    "run_time": ["0.29 min"],
    "outputs_time": ["3.74 min"],
    "total_time": ["4.03 min"],
    "total_iters": [200],
    "conv_msg": ["DECOMP.RSSD NOT converged", "NRMSE NOT converged"],
    "n_clusters": [4],
    "calibration_constraint": [0.1],
    "cores": [2],
    "iterations": [200],
    "trials": [1],
    "intercept": [true],
    "intercept_sign": ["non_negative"],
    "nevergrad_algo": ["TwoPointsDE"],
    "add_penalty_factor": [false],
    "seed": [123],
    "pareto_fronts": [13],
    "hyper_fixed": [false],
    "plot_folder": ["outputs/figures/robyn/Robyn_202604121947_init/"]
  },
  "Extras": {
    "raw_data": [
      {
        "date": "2022-07-04",
        "sales": 1010974.7309879948,
        "tv": 50218056.135685056,
        "youtube": 24821674.957395665,
        "facebook": 13507192.308386745,
        "instagram": 6315054.2223178074,
        "print_media": 4715606.0524281021,
        "radio": 46640913.327553771,
        "trade_spend": 1026000.7581785829,
        "cpi": 119.2703817246,
        "gdp_growth": 5.1237039829,
        "festival": 0.96749056076,
        "rainfall": 4.6150990176
      },
      {
        "date": "2022-07-11",
        "sales": 1330987.9290128597,
        "tv": 48943502.15366374,
        "youtube": 23521233.777148046,
        "facebook": 11819952.855525088,
        "instagram": 5886242.0409821179,
        "print_media": 4646868.0726417443,
        "radio": 44735668.543335222,
        "trade_spend": 5129494.8835614435,
        "cpi": 119.6590772995,
        "gdp_growth": 5.0532164756,
        "festival": 0.96749056076,
        "rainfall": 4.1924460349
      },
      {
        "date": "2022-07-18",
        "sales": 1570576.4305088811,
        "tv": 48648661.099090919,
        "youtube": 21778460.507475048,
        "facebook": 13363357.256249871,
        "instagram": 5692027.8271199977,
        "print_media": 4693192.5881621325,
        "radio": 47356066.518182904,
        "trade_spend": 6188054.2813977934,
        "cpi": 120.0442788561,
        "gdp_growth": 5.3999930614,
        "festival": 0.96749056076,
        "rainfall": 3.6868394212
      },
      {
        "date": "2022-07-25",
        "sales": 1315034.4252523968,
        "tv": 49762614.290751487,
        "youtube": 24922068.587075423,
        "facebook": 14061575.895161092,
        "instagram": 6390571.3069311939,
        "print_media": 4714153.7861711029,
        "radio": 43407359.253357023,
        "trade_spend": 743607.0365064208,
        "cpi": 120.4225433267,
        "gdp_growth": 5.7600167417,
        "festival": 0.96749056076,
        "rainfall": 4.2479278483
      },
      {
        "date": "2022-08-01",
        "sales": 1344600.2778557937,
        "tv": 51358143.063001767,
        "youtube": 24380887.810835153,
        "facebook": 13485328.24847143,
        "instagram": 6224710.387014173,
        "print_media": 4439110.2387100151,
        "radio": 48302408.901857369,
        "trade_spend": 781718.8113213878,
        "cpi": 120.790528802,
        "gdp_growth": 5.3149907322,
        "festival": 0.96749056076,
        "rainfall": 3.7526150701
      },
      {
        "date": "2022-08-08",
        "sales": 1375798.2082819468,
        "tv": 46961759.683003858,
        "youtube": 22599394.323900346,
        "facebook": 11744487.101075159,
        "instagram": 5694327.5748875849,
        "print_media": 4788315.4376697019,
        "radio": 47612205.70178432,
        "trade_spend": 698358.1473824155,
        "cpi": 121.1450432635,
        "gdp_growth": 5.370736471,
        "festival": 0.96749056076,
        "rainfall": 4.2875626396
      },
      {
        "date": "2022-08-15",
        "sales": 1207446.624566555,
        "tv": 50829788.623007178,
        "youtube": 22337190.754116725,
        "facebook": 10165962.0714936,
        "instagram": 5484034.3579727057,
        "print_media": 4479033.1827574419,
        "radio": 43232451.908964075,
        "trade_spend": 889360.1352759565,
        "cpi": 121.4830911305,
        "gdp_growth": 5.9407718366,
        "festival": 0.96749056076,
        "rainfall": 4.4003692566
      },
      {
        "date": "2022-08-22",
        "sales": 1542130.9794930429,
        "tv": 51864665.046373397,
        "youtube": 22124167.007435735,
        "facebook": 12774940.249125332,
        "instagram": 5702327.4263996808,
        "print_media": 4465120.914431395,
        "radio": 48426724.016501352,
        "trade_spend": 4839198.6105814427,
        "cpi": 121.8019169424,
        "gdp_growth": 5.6984355127,
        "festival": 0.96749056076,
        "rainfall": 3.799375858
      },
      {
        "date": "2022-08-29",
        "sales": 1129675.7537400741,
        "tv": 49925741.993103415,
        "youtube": 22369012.853421673,
        "facebook": 12067714.761307301,
        "instagram": 5680574.0468150647,
        "print_media": 4447856.5967215281,
        "radio": 43877353.079005174,
        "trade_spend": 1117272.0989597624,
        "cpi": 122.0990455392,
        "gdp_growth": 5.3004822866,
        "festival": 0.96749056076,
        "rainfall": 4.3410922846
      },
      {
        "date": "2022-09-05",
        "sales": 1579233.9201797841,
        "tv": 158953527.48049194,
        "youtube": 23806494.212917518,
        "facebook": 42672243.511549972,
        "instagram": 9028523.1937385015,
        "print_media": 4870497.7287378088,
        "radio": 15228093.148218324,
        "trade_spend": 5569831.9439456593,
        "cpi": 122.3723181553,
        "gdp_growth": 5.5468593644,
        "festival": 2.9024716823,
        "rainfall": 4.1739080391
      },
      {
        "date": "2022-09-12",
        "sales": 1461282.6996916952,
        "tv": 139936037.14914128,
        "youtube": 24072006.155425746,
        "facebook": 33463619.318070512,
        "instagram": 8160763.162892201,
        "print_media": 4631621.8619684651,
        "radio": 16525532.572935322,
        "trade_spend": 873344.1845710801,
        "cpi": 122.6199238992,
        "gdp_growth": 5.1670118246,
        "festival": 2.9024716823,
        "rainfall": 4.298182714
      },
      {
        "date": "2022-09-19",
        "sales": 1450426.9870997139,
        "tv": 143619875.50319815,
        "youtube": 21380652.508487619,
        "facebook": 35940854.302551627,
        "instagram": 7870215.931952687,
        "print_media": 4540327.2397514805,
        "radio": 15634861.608331116,
        "trade_spend": 961348.5682793525,
        "cpi": 122.8404261599,
        "gdp_growth": 5.0676094946,
        "festival": 2.9024716823,
        "rainfall": 4.6245175518
      },
      {
        "date": "2022-09-26",
        "sales": 2520509.3126630005,
        "tv": 145498803.8494747,
        "youtube": 22178095.863630187,
        "facebook": 36649363.104875207,
        "instagram": 8100555.4832135579,
        "print_media": 4676068.0785049107,
        "radio": 15076581.135564093,
        "trade_spend": 23287845.011828329,
        "cpi": 123.0327835564,
        "gdp_growth": 5.16672374,
        "festival": 2.9024716823,
        "rainfall": 3.9740597759
      },
      {
        "date": "2022-10-03",
        "sales": 1708743.3541304348,
        "tv": 157406515.44941822,
        "youtube": 23619984.434076697,
        "facebook": 40423051.6907745,
        "instagram": 8766302.0558927897,
        "print_media": 13989388.141566923,
        "radio": 15226855.216371197,
        "trade_spend": 1322949.9347828119,
        "cpi": 123.196365123,
        "gdp_growth": 4.4042596017,
        "festival": 2.9024716823,
        "rainfall": 0.78327599766
      },
      {
        "date": "2022-10-10",
        "sales": 2097167.5694479719,
        "tv": 158417656.56981805,
        "youtube": 21349248.898733418,
        "facebook": 37632832.964831278,
        "instagram": 8033133.0762298116,
        "print_media": 14019327.350057589,
        "radio": 14237138.266349483,
        "trade_spend": 4998179.6182440724,
        "cpi": 123.3309595107,
        "gdp_growth": 4.3414209061,
        "festival": 2.9024716823,
        "rainfall": 0.74204791078
      },
      {
        "date": "2022-10-17",
        "sales": 2317572.1703909859,
        "tv": 146110895.89200938,
        "youtube": 22090055.611595254,
        "facebook": 38726485.206531733,
        "instagram": 8290659.6429722244,
        "print_media": 13410107.441226952,
        "radio": 15020174.641390229,
        "trade_spend": 5366147.6780906674,
        "cpi": 123.4367780686,
        "gdp_growth": 4.5763457527,
        "festival": 2.9024716823,
        "rainfall": 0.7644276405
      },
      {
        "date": "2022-10-24",
        "sales": 2329040.6916263173,
        "tv": 144257553.51306784,
        "youtube": 19819016.812708508,
        "facebook": 36268340.200630203,
        "instagram": 7590637.3826047219,
        "print_media": 13681988.946201064,
        "radio": 15527424.37333709,
        "trade_spend": 5544434.375194761,
        "cpi": 123.5144517622,
        "gdp_growth": 4.3431349556,
        "festival": 2.9024716823,
        "rainfall": 0.98873114938
      },
      {
        "date": "2022-10-31",
        "sales": 2174461.4400911778,
        "tv": 149165294.55474097,
        "youtube": 24188151.705865007,
        "facebook": 32343037.153078366,
        "instagram": 8071934.056480838,
        "print_media": 13741166.877981814,
        "radio": 16077979.025937041,
        "trade_spend": 5178190.4035468809,
        "cpi": 123.5650219726,
        "gdp_growth": 4.6597637928,
        "festival": 2.9024716823,
        "rainfall": 1.1157308514
      },
      {
        "date": "2022-11-07",
        "sales": 1880435.3369995235,
        "tv": 146675123.09208852,
        "youtube": 23020262.185021911,
        "facebook": 38056440.240879275,
        "instagram": 8409696.46109231,
        "print_media": 14312925.528459648,
        "radio": 14818807.91779316,
        "trade_spend": 897567.2176639822,
        "cpi": 123.5899253107,
        "gdp_growth": 4.2391439753,
        "festival": 2.9024716823,
        "rainfall": 1.0961576823
      },
      {
        "date": "2022-11-14",
        "sales": 2094384.2904182456,
        "tv": 148510821.42888588,
        "youtube": 21779473.009645786,
        "facebook": 39865689.811368965,
        "instagram": 8342463.5830660546,
        "print_media": 13649240.161722597,
        "radio": 14840702.97509338,
        "trade_spend": 5464774.8981659925,
        "cpi": 123.5909726682,
        "gdp_growth": 4.0598992118,
        "festival": 2.9024716823,
        "rainfall": 1.2633107277
      },
      {
        "date": "2022-11-21",
        "sales": 2199613.9146744208,
        "tv": 158706473.98719326,
        "youtube": 23553566.0614179,
        "facebook": 33142542.695618432,
        "instagram": 8024967.4818454236,
        "print_media": 14819495.416857313,
        "radio": 16418269.232451573,
        "trade_spend": 5530853.4526016293,
        "cpi": 123.5703228107,
        "gdp_growth": 4.9190409328,
        "festival": 2.9024716823,
        "rainfall": 1.0160904553
      },
      {
        "date": "2022-11-28",
        "sales": 1584188.8879506437,
        "tv": 151371980.18908885,
        "youtube": 24570307.474999636,
        "facebook": 36845846.889862917,
        "instagram": 8598646.1839862205,
        "print_media": 14038379.469165049,
        "radio": 15182350.591741858,
        "trade_spend": 1189211.2879155858,
        "cpi": 123.530450898,
        "gdp_growth": 4.4428122199,
        "festival": 2.9024716823,
        "rainfall": 1.4534976204
      },
      {
        "date": "2022-12-05",
        "sales": 1582072.117098659,
        "tv": 48287426.036946423,
        "youtube": 66017869.541024089,
        "facebook": 14507427.853491545,
        "instagram": 14654316.693553973,
        "print_media": 4869533.1713951062,
        "radio": 15795329.14132856,
        "trade_spend": 520283.0885576065,
        "cpi": 123.4741123908,
        "gdp_growth": 4.5861118829,
        "festival": 0.96749056076,
        "rainfall": 0.9317813944
      },
      {
        "date": "2022-12-12",
        "sales": 1539315.7051636162,
        "tv": 48926525.691232301,
        "youtube": 63417439.336702347,
        "facebook": 12698603.915320927,
        "instagram": 13953348.258872563,
        "print_media": 4471964.9130808134,
        "radio": 15474038.317771567,
        "trade_spend": 4959286.4152393043,
        "cpi": 123.4043028698,
        "gdp_growth": 4.2201672762,
        "festival": 0.96749056076,
        "rainfall": 1.8381021917
      },
      {
        "date": "2022-12-19",
        "sales": 1415025.8341341538,
        "tv": 49278106.668063201,
        "youtube": 70272733.837136507,
        "facebook": 12048045.79884696,
        "instagram": 15259351.347312,
        "print_media": 4555908.3601924041,
        "radio": 15663197.463179225,
        "trade_spend": 667310.7853222474,
        "cpi": 123.3242143536,
        "gdp_growth": 4.5816907905,
        "festival": 0.96749056076,
        "rainfall": 1.2021218838
      },
      {
        "date": "2022-12-26",
        "sales": 1721044.3922661548,
        "tv": 48845643.635494299,
        "youtube": 68998794.866982058,
        "facebook": 13382245.119794825,
        "instagram": 15137983.485375896,
        "print_media": 4611201.6242053118,
        "radio": 16139034.954183966,
        "trade_spend": 4565630.3290056475,
        "cpi": 123.2371887513,
        "gdp_growth": 4.8894657803,
        "festival": 0.96749056076,
        "rainfall": 0.75187284099
      },
      {
        "date": "2023-01-02",
        "sales": 1887415.7228767441,
        "tv": 49976356.28974402,
        "youtube": 22443448.401373331,
        "facebook": 40630308.84247864,
        "instagram": 8551720.5645225309,
        "print_media": 4461021.984457355,
        "radio": 15427888.824946489,
        "trade_spend": 4504949.0337300012,
        "cpi": 123.1466691307,
        "gdp_growth": 4.6318214832,
        "festival": 1.9349811215,
        "rainfall": 0.68697377393
      },
      {
        "date": "2023-01-09",
        "sales": 1666667.6035882751,
        "tv": 51188524.415297896,
        "youtube": 23676543.353213128,
        "facebook": 41713915.586366512,
        "instagram": 8906700.2292792778,
        "print_media": 4724966.6549209896,
        "radio": 15661342.901040602,
        "trade_spend": 1042857.1553109505,
        "cpi": 123.0561495101,
        "gdp_growth": 5.2066472484,
        "festival": 1.9349811215,
        "rainfall": 1.1586417796
      },
      {
        "date": "2023-01-16",
        "sales": 2086786.7438086488,
        "tv": 49477755.042595156,
        "youtube": 23755218.178630952,
        "facebook": 34902611.087257467,
        "instagram": 8241304.7444519382,
        "print_media": 4360799.1520578144,
        "radio": 14796075.559204597,
        "trade_spend": 3797920.9537563124,
        "cpi": 122.9691239078,
        "gdp_growth": 5.0273357594,
        "festival": 1.9349811215,
        "rainfall": 0.9442896687
      },
      {
        "date": "2023-01-23",
        "sales": 2071859.8853148969,
        "tv": 52364128.311939232,
        "youtube": 23645530.258486699,
        "facebook": 36749786.29076568,
        "instagram": 8404084.6807739083,
        "print_media": 4669048.9807008849,
        "radio": 15858877.811786728,
        "trade_spend": 4837636.454614724,
        "cpi": 122.8890353915,
        "gdp_growth": 5.218275772,
        "festival": 1.9349811215,
        "rainfall": 1.2289436039
      },
      {
        "date": "2023-01-30",
        "sales": 1713184.60403333,
        "tv": 50047323.574392512,
        "youtube": 22745615.705121953,
        "facebook": 35020661.80991143,
        "instagram": 8051189.3220155342,
        "print_media": 4770889.6720993975,
        "radio": 16269227.677462138,
        "trade_spend": 1310777.7985025446,
        "cpi": 122.8192258705,
        "gdp_growth": 5.2052667794,
        "festival": 1.9349811215,
        "rainfall": 1.1558377023
      },
      {
        "date": "2023-02-06",
        "sales": 2157189.0486349948,
        "tv": 52106896.41382286,
        "youtube": 23711833.274510067,
        "facebook": 35281779.534419082,
        "instagram": 8270544.6083439216,
        "print_media": 4749260.3922272846,
        "radio": 15232080.701942964,
        "trade_spend": 5621637.1891626073,
        "cpi": 122.7628873633,
        "gdp_growth": 5.9935842469,
        "festival": 0.96749056076,
        "rainfall": 0.99002855317
      },
      {
        "date": "2023-02-13",
        "sales": 1730720.2163546176,
        "tv": 51473089.593493097,
        "youtube": 24224408.027390443,
        "facebook": 33585065.377003953,
        "instagram": 8203388.1431784835,
        "print_media": 4865102.7939082179,
        "radio": 16714134.111104293,
        "trade_spend": 968429.9226651039,
        "cpi": 122.7230154506,
        "gdp_growth": 5.4653075407,
        "festival": 0.96749056076,
        "rainfall": 0.75501974544
      },
      {
        "date": "2023-02-20",
        "sales": 1535717.769691803,
        "tv": 47422786.677450441,
        "youtube": 23389027.267992638,
        "facebook": 39835385.706817888,
        "instagram": 8661344.0242803171,
        "print_media": 4794846.2276689159,
        "radio": 15807650.789619446,
        "trade_spend": 809499.8307024878,
        "cpi": 122.7023655931,
        "gdp_growth": 5.1535832964,
        "festival": 0.96749056076,
        "rainfall": 0.55217013653
      },
      {
        "date": "2023-02-27",
        "sales": 1431921.3910419317,
        "tv": 51213634.722526103,
        "youtube": 24658974.186812215,
        "facebook": 33462128.957455989,
        "instagram": 8278007.7331080418,
        "print_media": 4332569.6943145543,
        "radio": 15697982.421985136,
        "trade_spend": 1012502.7039637929,
        "cpi": 122.7034129506,
        "gdp_growth": 5.6861827784,
        "festival": 0.96749056076,
        "rainfall": 0.87656149372
      },
      {
        "date": "2023-03-06",
        "sales": 1416540.6862362176,
        "tv": 48318371.926632829,
        "youtube": 66543214.042544521,
        "facebook": 14084943.794932634,
        "instagram": 14717137.188002169,
        "print_media": 4571619.8651512181,
        "radio": 15196339.924033426,
        "trade_spend": 936602.7164049589,
        "cpi": 122.7283162887,
        "gdp_growth": 5.0204386887,
        "festival": 0.96749056076,
        "rainfall": 1.2721818165
      },
      {
        "date": "2023-03-13",
        "sales": 1492336.9941277415,
        "tv": 49394932.05358661,
        "youtube": 69370840.143166244,
        "facebook": 12096201.8435752,
        "instagram": 15083788.21299077,
        "print_media": 4412448.2883904884,
        "radio": 15026564.06418163,
        "trade_spend": 813324.369297113,
        "cpi": 122.7788864992,
        "gdp_growth": 5.3677048202,
        "festival": 0.96749056076,
        "rainfall": 1.0771505399
      },
      {
        "date": "2023-03-20",
        "sales": 1423441.6112405043,
        "tv": 53904675.716922261,
        "youtube": 74040211.373005331,
        "facebook": 12638718.905108135,
        "instagram": 16071914.165111881,
        "print_media": 4969840.6749080485,
        "radio": 16799211.915051311,
        "trade_spend": 1024069.4869399095,
        "cpi": 122.8565601928,
        "gdp_growth": 4.6216304473,
        "festival": 0.96749056076,
        "rainfall": 0.63388296713
      },
      {
        "date": "2023-03-27",
        "sales": 1546861.8082700009,
        "tv": 51097733.599763758,
        "youtube": 68761046.039526805,
        "facebook": 13027886.885866802,
        "instagram": 15054997.896492042,
        "print_media": 4314656.4334620479,
        "radio": 14994081.741064301,
        "trade_spend": 1269731.6766936304,
        "cpi": 122.9623787506,
        "gdp_growth": 4.697994689,
        "festival": 0.96749056076,
        "rainfall": 1.0647276589
      },
      {
        "date": "2023-04-03",
        "sales": 1650553.2701200014,
        "tv": 52406087.273027971,
        "youtube": 70108624.045069471,
        "facebook": 12383177.652203184,
        "instagram": 15260042.574234216,
        "print_media": 4498824.2352196146,
        "radio": 15826392.970119152,
        "trade_spend": 897405.8489348004,
        "cpi": 123.0969731383,
        "gdp_growth": 5.0341902908,
        "festival": 0.96749056076,
        "rainfall": 1.1291413567
      },
      {
        "date": "2023-04-10",
        "sales": 1655837.9965203034,
        "tv": 50975493.592645079,
        "youtube": 65697690.242518447,
        "facebook": 12711669.858974904,
        "instagram": 14410705.03440118,
        "print_media": 4480422.4045356326,
        "radio": 15461166.138884943,
        "trade_spend": 1067340.724634551,
        "cpi": 123.2605547049,
        "gdp_growth": 5.0768035593,
        "festival": 0.96749056076,
        "rainfall": 0.74376561586
      },
      {
        "date": "2023-04-17",
        "sales": 1780988.8254102448,
        "tv": 51378287.515695758,
        "youtube": 71252051.007432312,
        "facebook": 10808095.536133902,
        "instagram": 15331219.755099854,
        "print_media": 4443549.6983066034,
        "radio": 14404993.621588709,
        "trade_spend": 691697.2304045416,
        "cpi": 123.4529121014,
        "gdp_growth": 4.7953605982,
        "festival": 0.96749056076,
        "rainfall": 1.0588200401
      },
      {
        "date": "2023-04-24",
        "sales": 1780573.8687392636,
        "tv": 51709279.986497819,
        "youtube": 73166636.951112211,
        "facebook": 12161079.066339895,
        "instagram": 15849435.296856433,
        "print_media": 4568528.6360921618,
        "radio": 15384356.750657355,
        "trade_spend": 754552.9323662356,
        "cpi": 123.6734143621,
        "gdp_growth": 4.6109667615,
        "festival": 0.96749056076,
        "rainfall": 1.0298171808
      },
      {
        "date": "2023-05-01",
        "sales": 2048659.2676060451,
        "tv": 49999588.695425555,
        "youtube": 64890294.348570988,
        "facebook": 13652085.189155845,
        "instagram": 14343267.388629783,
        "print_media": 4598878.4771495946,
        "radio": 16839202.61044443,
        "trade_spend": 6707515.0151738469,
        "cpi": 123.921020106,
        "gdp_growth": 4.4760659219,
        "festival": 0.96749056076,
        "rainfall": 0.66508787205
      },
      {
        "date": "2023-05-08",
        "sales": 1556141.0907238219,
        "tv": 47672231.899523631,
        "youtube": 66406136.035668828,
        "facebook": 11306984.371298134,
        "instagram": 14411925.64426358,
        "print_media": 4662233.0425014272,
        "radio": 14782281.22987134,
        "trade_spend": 1209974.4727856154,
        "cpi": 124.1942927222,
        "gdp_growth": 4.0688358951,
        "festival": 0.96749056076,
        "rainfall": 1.1207820657
      },
      {
        "date": "2023-05-15",
        "sales": 1634809.0351363244,
        "tv": 54093305.400686324,
        "youtube": 70635606.012565076,
        "facebook": 12280056.583035015,
        "instagram": 15355126.860816516,
        "print_media": 4391098.2681916133,
        "radio": 15050295.002742283,
        "trade_spend": 999389.1857613279,
        "cpi": 124.491421319,
        "gdp_growth": 4.2666159129,
        "festival": 0.96749056076,
        "rainfall": 1.182420685
      },
      {
        "date": "2023-05-22",
        "sales": 1730833.9078700056,
        "tv": 53061473.214229017,
        "youtube": 72705097.141129747,
        "facebook": 12596350.199399246,
        "instagram": 15800654.448165877,
        "print_media": 4318222.3438019389,
        "radio": 14666300.938699674,
        "trade_spend": 874611.1441461947,
        "cpi": 124.8102471308,
        "gdp_growth": 4.3439953025,
        "festival": 0.96749056076,
        "rainfall": 1.341003191
      },
      {
        "date": "2023-05-29",
        "sales": 2042804.5816542341,
        "tv": 50225194.657006077,
        "youtube": 66218908.82857912,
        "facebook": 12444672.484334001,
        "instagram": 14488249.014149224,
        "print_media": 4617490.7493038978,
        "radio": 16110119.168388307,
        "trade_spend": 4664883.6824980984,
        "cpi": 125.1482949978,
        "gdp_growth": 4.8257899304,
        "festival": 0.96749056076,
        "rainfall": 1.332121886
      },
      {
        "date": "2023-06-05",
        "sales": 1932405.820976817,
        "tv": 50100342.737236254,
        "youtube": 22752273.357980974,
        "facebook": 12105000.985669062,
        "instagram": 5760954.7701631011,
        "print_media": 4695354.2108849166,
        "radio": 48716657.170983762,
        "trade_spend": 5702355.4269019468,
        "cpi": 125.5028094593,
        "gdp_growth": 4.6685317675,
        "festival": 0.96749056076,
        "rainfall": 3.6302507743
      },
      {
        "date": "2023-06-12",
        "sales": 1814411.4356106599,
        "tv": 50583452.030329615,
        "youtube": 21546506.673152935,
        "facebook": 13618295.683360068,
        "instagram": 5671130.9029665943,
        "print_media": 4653230.0577995488,
        "radio": 49548513.180786282,
        "trade_spend": 6756819.6776984707,
        "cpi": 125.8707949346,
        "gdp_growth": 4.1191785533,
        "festival": 0.96749056076,
        "rainfall": 3.763806319
      },
      {
        "date": "2023-06-19",
        "sales": 1529526.945041257,
        "tv": 49745636.42451936,
        "youtube": 24006599.012828875,
        "facebook": 12669798.255825801,
        "instagram": 6068299.6281483555,
        "print_media": 4816247.0306076463,
        "radio": 46566239.88331227,
        "trade_spend": 1097678.2054039217,
        "cpi": 126.2490594052,
        "gdp_growth": 4.8409500999,
        "festival": 0.96749056076,
        "rainfall": 4.2049568289
      },
      {
        "date": "2023-06-26",
        "sales": 2302228.3414613158,
        "tv": 46129838.981580622,
        "youtube": 20254765.003569424,
        "facebook": 12112691.475705149,
        "instagram": 5262222.1482843999,
        "print_media": 4839947.1921649761,
        "radio": 45512424.578287721,
        "trade_spend": 6014689.2485295357,
        "cpi": 126.6342609618,
        "gdp_growth": 4.7413957611,
        "festival": 0.96749056076,
        "rainfall": 4.2045774831
      },
      {
        "date": "2023-07-03",
        "sales": 1708072.6843868848,
        "tv": 49137737.145380676,
        "youtube": 23812510.633138396,
        "facebook": 12693920.573266475,
        "instagram": 6031894.1839543264,
        "print_media": 4762364.7120030737,
        "radio": 40687035.717443824,
        "trade_spend": 845316.9776549062,
        "cpi": 127.0229565367,
        "gdp_growth": 4.7733438589,
        "festival": 0.96749056076,
        "rainfall": 4.2049605999
      },
      {
        "date": "2023-07-10",
        "sales": 1650326.8485883977,
        "tv": 50929172.40705663,
        "youtube": 23766512.084122978,
        "facebook": 11833450.315592902,
        "instagram": 5936647.4483838864,
        "print_media": 4315572.8445667848,
        "radio": 46570542.194533393,
        "trade_spend": 982644.0808023468,
        "cpi": 127.4116521116,
        "gdp_growth": 5.2770927403,
        "festival": 0.96749056076,
        "rainfall": 5.2184241139
      },
      {
        "date": "2023-07-17",
        "sales": 2250918.8662023409,
        "tv": 50608760.106320202,
        "youtube": 20965332.985775992,
        "facebook": 12560962.585258298,
        "instagram": 5449162.8556810282,
        "print_media": 4690063.3976504058,
        "radio": 47400619.262041807,
        "trade_spend": 5435188.7849829523,
        "cpi": 127.7968536682,
        "gdp_growth": 5.5144211009,
        "festival": 0.96749056076,
        "rainfall": 4.2219168691
      },
      {
        "date": "2023-07-24",
        "sales": 1658411.4316252463,
        "tv": 48874621.137306795,
        "youtube": 23253732.53883623,
        "facebook": 13033452.428151395,
        "instagram": 5954091.7505823858,
        "print_media": 4559879.8232017551,
        "radio": 43404593.734452799,
        "trade_spend": 920688.8899179961,
        "cpi": 128.1751181388,
        "gdp_growth": 5.583364454,
        "festival": 0.96749056076,
        "rainfall": 4.3933763825
      },
      {
        "date": "2023-07-31",
        "sales": 1942845.7704784574,
        "tv": 44918370.968404196,
        "youtube": 22963953.462140497,
        "facebook": 11681554.554435503,
        "instagram": 5760946.1478716498,
        "print_media": 4563834.9927412961,
        "radio": 45130406.115010545,
        "trade_spend": 1324850.1555131683,
        "cpi": 128.5431036141,
        "gdp_growth": 5.1343637555,
        "festival": 0.96749056076,
        "rainfall": 4.3382458263
      },
      {
        "date": "2023-08-07",
        "sales": 1720828.459394472,
        "tv": 48845688.141867317,
        "youtube": 23394981.473383751,
        "facebook": 13955937.036493115,
        "instagram": 6074589.9983260622,
        "print_media": 4826969.5759963784,
        "radio": 39937552.800086781,
        "trade_spend": 886933.1681595378,
        "cpi": 128.8976180756,
        "gdp_growth": 5.3483245566,
        "festival": 0.96749056076,
        "rainfall": 4.2463603359
      },
      {
        "date": "2023-08-14",
        "sales": 2041140.6712913483,
        "tv": 48521169.999053471,
        "youtube": 23801612.58328636,
        "facebook": 14859037.990985887,
        "instagram": 6246226.3157558609,
        "print_media": 5106260.9144705795,
        "radio": 46055807.960375085,
        "trade_spend": 4531411.3469426828,
        "cpi": 129.2356659426,
        "gdp_growth": 5.5682273306,
        "festival": 0.96749056076,
        "rainfall": 3.9528408773
      },
      {
        "date": "2023-08-21",
        "sales": 1515668.4501230838,
        "tv": 53389843.426056817,
        "youtube": 22963825.886478517,
        "facebook": 12133621.219210073,
        "instagram": 5806127.299216711,
        "print_media": 4923047.827834812,
        "radio": 41049694.291687578,
        "trade_spend": 812194.4897147547,
        "cpi": 129.5544917545,
        "gdp_growth": 5.7605617386,
        "festival": 0.96749056076,
        "rainfall": 4.2790256071
      },
      {
        "date": "2023-08-28",
        "sales": 1555987.0119327512,
        "tv": 48595825.176778898,
        "youtube": 23163545.809048209,
        "facebook": 11784150.811886892,
        "instagram": 5811124.2429983309,
        "print_media": 4848783.0464971745,
        "radio": 46940058.675512433,
        "trade_spend": 1071900.2592963008,
        "cpi": 129.8516203513,
        "gdp_growth": 5.297586635,
        "festival": 0.96749056076,
        "rainfall": 3.8139073209
      },
      {
        "date": "2023-09-04",
        "sales": 1733449.100673958,
        "tv": 149545109.57113016,
        "youtube": 23473367.580827493,
        "facebook": 37769856.947852559,
        "instagram": 8471659.2109507546,
        "print_media": 4757991.3864470096,
        "radio": 15035013.986035625,
        "trade_spend": 899212.1231055411,
        "cpi": 130.1248929674,
        "gdp_growth": 5.3294675385,
        "festival": 2.9024716823,
        "rainfall": 3.9766618454
      },
      {
        "date": "2023-09-11",
        "sales": 2213098.7027579043,
        "tv": 162348637.37966949,
        "youtube": 22191279.904152568,
        "facebook": 42689301.581159703,
        "instagram": 8707186.1389464848,
        "print_media": 4417582.5586221544,
        "radio": 15212305.521988954,
        "trade_spend": 4759227.0231426088,
        "cpi": 130.3724987113,
        "gdp_growth": 4.9750847288,
        "festival": 2.9024716823,
        "rainfall": 3.9011929741
      },
      {
        "date": "2023-09-18",
        "sales": 1904830.4425127157,
        "tv": 130983884.04582426,
        "youtube": 21431439.077747446,
        "facebook": 36501004.898712434,
        "instagram": 7936388.3054207331,
        "print_media": 4710828.8877151916,
        "radio": 15576952.698335273,
        "trade_spend": 1179592.7895346573,
        "cpi": 130.593000972,
        "gdp_growth": 4.8495436432,
        "festival": 2.9024716823,
        "rainfall": 4.0734305896
      },
      {
        "date": "2023-09-25",
        "sales": 2422790.4802718745,
        "tv": 154754661.85008946,
        "youtube": 22503424.203055389,
        "facebook": 38929265.694025986,
        "instagram": 8393611.4100136776,
        "print_media": 4891989.5239693858,
        "radio": 14919731.391135639,
        "trade_spend": 5780354.7442382909,
        "cpi": 130.7853583685,
        "gdp_growth": 5.3370514143,
        "festival": 2.9024716823,
        "rainfall": 4.75139941
      },
      {
        "date": "2023-10-02",
        "sales": 2381970.3669152134,
        "tv": 151443611.58770737,
        "youtube": 23904016.46918628,
        "facebook": 37619104.109433904,
        "instagram": 8542713.7047806475,
        "print_media": 13286428.926467372,
        "radio": 14875329.043483129,
        "trade_spend": 820987.0324802442,
        "cpi": 130.9489399351,
        "gdp_growth": 5.3802942316,
        "festival": 2.9024716823,
        "rainfall": 0.44516097295
      },
      {
        "date": "2023-10-09",
        "sales": 2243997.9406993147,
        "tv": 146137678.15855953,
        "youtube": 25424132.833340671,
        "facebook": 38666802.595271811,
        "instagram": 8951506.8261953164,
        "print_media": 13422797.593241099,
        "radio": 15551878.658278871,
        "trade_spend": 584722.2125053924,
        "cpi": 131.0835343228,
        "gdp_growth": 4.8348557317,
        "festival": 2.9024716823,
        "rainfall": 1.2205204616
      },
      {
        "date": "2023-10-16",
        "sales": 2800952.841786182,
        "tv": 157387921.91092476,
        "youtube": 23020710.859324127,
        "facebook": 37607689.179305114,
        "instagram": 8364911.0897953371,
        "print_media": 13242561.469844721,
        "radio": 14671086.647894876,
        "trade_spend": 5284540.1414840156,
        "cpi": 131.1893528807,
        "gdp_growth": 5.0437828179,
        "festival": 2.9024716823,
        "rainfall": 0.52245303083
      },
      {
        "date": "2023-10-23",
        "sales": 3236289.4558037641,
        "tv": 142340178.17031431,
        "youtube": 24608168.370422572,
        "facebook": 42378830.40586032,
        "instagram": 9159516.7146705464,
        "print_media": 13735473.928060917,
        "radio": 15662732.104384266,
        "trade_spend": 5039580.9130981211,
        "cpi": 131.2670265743,
        "gdp_growth": 4.7534482186,
        "festival": 2.9024716823,
        "rainfall": 0.86884383195
      },
      {
        "date": "2023-10-30",
        "sales": 2723044.7157035144,
        "tv": 143484712.26854324,
        "youtube": 22122633.716814488,
        "facebook": 39903141.585833736,
        "instagram": 8414840.9019462708,
        "print_media": 14425868.386506466,
        "radio": 14279879.339911539,
        "trade_spend": 5448654.3960421421,
        "cpi": 131.3175967847,
        "gdp_growth": 4.3733684132,
        "festival": 2.9024716823,
        "rainfall": 1.3427944871
      },
      {
        "date": "2023-11-06",
        "sales": 3699642.7252511112,
        "tv": 152990114.16834858,
        "youtube": 23588498.21310563,
        "facebook": 38902927.052425101,
        "instagram": 8607992.3478636369,
        "print_media": 13065448.031469751,
        "radio": 14410812.071869725,
        "trade_spend": 11493000.834741198,
        "cpi": 131.3425001228,
        "gdp_growth": 4.618097909,
        "festival": 2.9024716823,
        "rainfall": 1.0316606873
      },
      {
        "date": "2023-11-13",
        "sales": 3084003.2694588406,
        "tv": 142881100.8118313,
        "youtube": 21282074.787261412,
        "facebook": 39575218.62431065,
        "instagram": 8213936.8198833475,
        "print_media": 14289545.194573479,
        "radio": 15685554.467778804,
        "trade_spend": 5931305.6709580813,
        "cpi": 131.3435474803,
        "gdp_growth": 4.9406505242,
        "festival": 2.9024716823,
        "rainfall": 0.68489312877
      },
      {
        "date": "2023-11-20",
        "sales": 2275399.400037772,
        "tv": 148609339.75550631,
        "youtube": 23676852.865193587,
        "facebook": 32139407.987719536,
        "instagram": 7949311.3718106709,
        "print_media": 13182430.562285617,
        "radio": 15326917.085389335,
        "trade_spend": 707017.7688320802,
        "cpi": 131.3228976228,
        "gdp_growth": 4.470812665,
        "festival": 2.9024716823,
        "rainfall": 0.7949457343
      },
      {
        "date": "2023-11-27",
        "sales": 2212989.6659241552,
        "tv": 150549759.894952,
        "youtube": 22150053.030826852,
        "facebook": 37931710.70664975,
        "instagram": 8223181.6768303467,
        "print_media": 13559495.543089107,
        "radio": 14584723.538733795,
        "trade_spend": 1069394.5424650074,
        "cpi": 131.2830257101,
        "gdp_growth": 4.9772979344,
        "festival": 2.9024716823,
        "rainfall": 1.2184974595
      },
      {
        "date": "2023-12-04",
        "sales": 2763798.1649896461,
        "tv": 50334513.057322413,
        "youtube": 68003163.703253612,
        "facebook": 13519530.233316455,
        "instagram": 14952585.763982369,
        "print_media": 4545665.3801028961,
        "radio": 15211577.553499585,
        "trade_spend": 13546630.187073298,
        "cpi": 131.2266872029,
        "gdp_growth": 3.7838927222,
        "festival": 0.96749056076,
        "rainfall": 0.79037198699
      },
      {
        "date": "2023-12-11",
        "sales": 2372633.2600606796,
        "tv": 51858574.353480302,
        "youtube": 76007081.821006045,
        "facebook": 12871131.644582512,
        "instagram": 16488529.528659461,
        "print_media": 4585366.902254832,
        "radio": 13981128.039876986,
        "trade_spend": 4073576.631554645,
        "cpi": 131.1568776819,
        "gdp_growth": 4.8908494228,
        "festival": 0.96749056076,
        "rainfall": 1.0778686081
      },
      {
        "date": "2023-12-18",
        "sales": 1767946.9126533973,
        "tv": 52491371.213915236,
        "youtube": 71845534.894007549,
        "facebook": 11252231.114220731,
        "instagram": 15494330.090223584,
        "print_media": 4382953.1740838215,
        "radio": 15990781.625046216,
        "trade_spend": 857074.2397780137,
        "cpi": 131.0767891657,
        "gdp_growth": 4.77018858,
        "festival": 0.96749056076,
        "rainfall": 1.0259800842
      },
      {
        "date": "2023-12-25",
        "sales": 2107044.7858939418,
        "tv": 51162191.855081439,
        "youtube": 66489343.357749686,
        "facebook": 11276743.340965925,
        "instagram": 14425543.005646531,
        "print_media": 4819371.4777730191,
        "radio": 14574316.276249487,
        "trade_spend": 4006732.7748623602,
        "cpi": 130.9897635634,
        "gdp_growth": 4.7670913082,
        "festival": 0.96749056076,
        "rainfall": 0.81428879869
      },
      {
        "date": "2024-01-01",
        "sales": 2611528.8645586609,
        "tv": 51905009.00851319,
        "youtube": 23635134.059284076,
        "facebook": 40632166.124959916,
        "instagram": 8790243.4243528061,
        "print_media": 4513673.1925364574,
        "radio": 15367190.033569818,
        "trade_spend": 5329525.0110081751,
        "cpi": 130.8992439428,
        "gdp_growth": 5.0028151412,
        "festival": 1.9349811215,
        "rainfall": 1.6631356203
      },
      {
        "date": "2024-01-08",
        "sales": 2508825.6489734966,
        "tv": 50202851.943072751,
        "youtube": 20784652.847243842,
        "facebook": 39100554.342270203,
        "instagram": 8066986.0036757896,
        "print_media": 4806430.9946343442,
        "radio": 14263501.511019457,
        "trade_spend": 4883257.9886239599,
        "cpi": 130.8087243222,
        "gdp_growth": 4.5011521992,
        "festival": 1.9349811215,
        "rainfall": 1.204627445
      },
      {
        "date": "2024-01-15",
        "sales": 2950496.9627695135,
        "tv": 47249571.342622183,
        "youtube": 23605606.638234705,
        "facebook": 37883533.184890002,
        "instagram": 8509474.6461359411,
        "print_media": 4885388.1131622996,
        "radio": 15588471.959362706,
        "trade_spend": 13195766.699785175,
        "cpi": 130.7216987199,
        "gdp_growth": 5.141064001,
        "festival": 1.9349811215,
        "rainfall": 0.39722264567
      },
      {
        "date": "2024-01-22",
        "sales": 2150761.6371606756,
        "tv": 52060546.295745984,
        "youtube": 23087711.180504873,
        "facebook": 34851717.337272778,
        "instagram": 8102713.9698282536,
        "print_media": 4587590.6432848508,
        "radio": 15829985.068911059,
        "trade_spend": 641132.8739635953,
        "cpi": 130.6416102036,
        "gdp_growth": 5.4119608954,
        "festival": 1.9349811215,
        "rainfall": 1.0687580273
      },
      {
        "date": "2024-01-29",
        "sales": 2576448.2522223531,
        "tv": 49553606.10399726,
        "youtube": 23319812.163709559,
        "facebook": 38279193.733327053,
        "instagram": 8491881.8060746174,
        "print_media": 4465946.4080855399,
        "radio": 15571178.310565047,
        "trade_spend": 5268711.0370715894,
        "cpi": 130.5718006826,
        "gdp_growth": 5.826080259,
        "festival": 1.9349811215,
        "rainfall": 0.81119585799
      },
      {
        "date": "2024-02-05",
        "sales": 2231526.9250407857,
        "tv": 53729700.479763843,
        "youtube": 25049847.953891732,
        "facebook": 42035900.345997937,
        "instagram": 9213559.6253781412,
        "print_media": 4877919.0449205469,
        "radio": 15169451.497153772,
        "trade_spend": 952503.0639850029,
        "cpi": 130.5154621754,
        "gdp_growth": 5.2859154944,
        "festival": 0.96749056076,
        "rainfall": 1.2709777334
      },
      {
        "date": "2024-02-12",
        "sales": 1962254.9967548358,
        "tv": 48863006.486514047,
        "youtube": 25629139.147394828,
        "facebook": 38985600.2155203,
        "instagram": 9024387.8510309961,
        "print_media": 4516108.2763199713,
        "radio": 17476162.779685728,
        "trade_spend": 765311.1984843093,
        "cpi": 130.4755902627,
        "gdp_growth": 5.2279809818,
        "festival": 0.96749056076,
        "rainfall": 0.77149934263
      },
      {
        "date": "2024-02-19",
        "sales": 2046059.4716650392,
        "tv": 50103093.929577939,
        "youtube": 21397522.358303014,
        "facebook": 35843984.434698783,
        "instagram": 7863902.9151304811,
        "print_media": 4502785.5498899808,
        "radio": 16409107.368557442,
        "trade_spend": 684785.2222946067,
        "cpi": 130.4549404052,
        "gdp_growth": 5.3195496155,
        "festival": 0.96749056076,
        "rainfall": 0.97730363556
      },
      {
        "date": "2024-02-26",
        "sales": 1856420.3401316991,
        "tv": 48360075.69683259,
        "youtube": 25316827.661907975,
        "facebook": 38458476.246181533,
        "instagram": 8909213.1569997482,
        "print_media": 4761565.9928574516,
        "radio": 14783034.197965739,
        "trade_spend": 897738.6421197258,
        "cpi": 130.4559877627,
        "gdp_growth": 5.7139030066,
        "festival": 0.96749056076,
        "rainfall": 1.1654782549
      },
      {
        "date": "2024-03-04",
        "sales": 1941848.1143766721,
        "tv": 50127824.781678908,
        "youtube": 71105634.341135308,
        "facebook": 12048523.388141438,
        "instagram": 15425979.207041208,
        "print_media": 4735282.173466824,
        "radio": 14051904.849410694,
        "trade_spend": 1105014.9998340574,
        "cpi": 130.4808911008,
        "gdp_growth": 5.4830319811,
        "festival": 0.96749056076,
        "rainfall": 1.2750228195
      },
      {
        "date": "2024-03-11",
        "sales": 2103572.8726677066,
        "tv": 52256045.160431787,
        "youtube": 66067756.809290066,
        "facebook": 13081401.718574911,
        "instagram": 14521691.533715505,
        "print_media": 4728479.3087469507,
        "radio": 14974487.114410048,
        "trade_spend": 4617545.2950730873,
        "cpi": 130.5314613113,
        "gdp_growth": 5.1472069044,
        "festival": 0.96749056076,
        "rainfall": 0.64768121417
      },
      {
        "date": "2024-03-18",
        "sales": 2365598.8292233208,
        "tv": 48660842.918872319,
        "youtube": 66616040.147239842,
        "facebook": 13410969.183896035,
        "instagram": 14664304.947837573,
        "print_media": 4706199.0839913068,
        "radio": 16656076.987131957,
        "trade_spend": 5812584.6713634189,
        "cpi": 130.6091350049,
        "gdp_growth": 5.3598649562,
        "festival": 0.96749056076,
        "rainfall": 0.9105736474
      },
      {
        "date": "2024-03-25",
        "sales": 1966439.7012985612,
        "tv": 48773296.275946043,
        "youtube": 64624556.992350355,
        "facebook": 13117579.368074406,
        "instagram": 14236669.335277513,
        "print_media": 4413037.6521602068,
        "radio": 15347805.467216773,
        "trade_spend": 662231.6449214082,
        "cpi": 130.7149535627,
        "gdp_growth": 5.12347198,
        "festival": 0.96749056076,
        "rainfall": 0.86792882109
      },
      {
        "date": "2024-04-01",
        "sales": 2511535.7655709111,
        "tv": 51288354.253472365,
        "youtube": 72194292.918728605,
        "facebook": 11884947.114223465,
        "instagram": 15627353.295168068,
        "print_media": 4537714.1401632009,
        "radio": 15945284.950590566,
        "trade_spend": 5593666.0274669183,
        "cpi": 130.8495479504,
        "gdp_growth": 5.2645872936,
        "festival": 0.96749056076,
        "rainfall": 0.8137638353
      },
      {
        "date": "2024-04-08",
        "sales": 2854788.2372585619,
        "tv": 50001125.523175091,
        "youtube": 70198844.569496781,
        "facebook": 12340137.784490265,
        "instagram": 15273782.692348383,
        "print_media": 4681833.9858317329,
        "radio": 15413169.739383092,
        "trade_spend": 5719805.1384242764,
        "cpi": 131.013129517,
        "gdp_growth": 4.6467719433,
        "festival": 0.96749056076,
        "rainfall": 1.5482099188
      },
      {
        "date": "2024-04-15",
        "sales": 2383773.6922001448,
        "tv": 50337490.45540332,
        "youtube": 67390512.215570554,
        "facebook": 12825222.439374385,
        "instagram": 14760624.687051551,
        "print_media": 4728591.5961899552,
        "radio": 14582277.349253623,
        "trade_spend": 1000885.491689851,
        "cpi": 131.2054869135,
        "gdp_growth": 4.6463873733,
        "festival": 0.96749056076,
        "rainfall": 1.1351122885
      },
      {
        "date": "2024-04-22",
        "sales": 2068107.9536223533,
        "tv": 48884489.181542449,
        "youtube": 70879111.727961704,
        "facebook": 12611556.948536202,
        "instagram": 15436978.040445963,
        "print_media": 4479747.2786945663,
        "radio": 15444862.343552601,
        "trade_spend": 1098528.0699533615,
        "cpi": 131.4259891742,
        "gdp_growth": 4.5284364864,
        "festival": 0.96749056076,
        "rainfall": 0.62928424424
      },
      {
        "date": "2024-04-29",
        "sales": 2280711.9216713817,
        "tv": 47772891.683303133,
        "youtube": 62146081.552931868,
        "facebook": 13421154.341886848,
        "instagram": 13771331.744775059,
        "print_media": 4606222.2930030748,
        "radio": 15389636.177228505,
        "trade_spend": 4508114.8505119057,
        "cpi": 131.6735949181,
        "gdp_growth": 4.1290567151,
        "festival": 0.96749056076,
        "rainfall": 1.2908446577
      },
      {
        "date": "2024-05-06",
        "sales": 3056867.6535098357,
        "tv": 50271435.938493453,
        "youtube": 71139915.223471433,
        "facebook": 13302929.424529254,
        "instagram": 15558275.987147214,
        "print_media": 4655586.5647266768,
        "radio": 14981805.050186887,
        "trade_spend": 5243910.4696584465,
        "cpi": 131.9468675343,
        "gdp_growth": 4.5986115698,
        "festival": 0.96749056076,
        "rainfall": 1.6565198846
      },
      {
        "date": "2024-05-13",
        "sales": 2942690.2024805071,
        "tv": 51130527.414043114,
        "youtube": 76215604.715884387,
        "facebook": 13092405.656953255,
        "instagram": 16552361.508872204,
        "print_media": 4599563.7871462665,
        "radio": 15924302.986522773,
        "trade_spend": 6123220.4005235825,
        "cpi": 132.2439961311,
        "gdp_growth": 4.5594392574,
        "festival": 0.96749056076,
        "rainfall": 1.3256431238
      },
      {
        "date": "2024-05-20",
        "sales": 3148467.3799306671,
        "tv": 49100650.943889432,
        "youtube": 62412707.577864237,
        "facebook": 13195314.992892301,
        "instagram": 13802073.014862079,
        "print_media": 4672100.8389963508,
        "radio": 13840211.121694379,
        "trade_spend": 14239938.420165138,
        "cpi": 132.5628219429,
        "gdp_growth": 4.4830341416,
        "festival": 0.96749056076,
        "rainfall": 0.5507968389
      },
      {
        "date": "2024-05-27",
        "sales": 2579563.0083538936,
        "tv": 49957282.085253194,
        "youtube": 66370945.607880205,
        "facebook": 13821891.981889429,
        "instagram": 14656378.319764985,
        "print_media": 4563630.5906819636,
        "radio": 15230499.208857704,
        "trade_spend": 5910722.0628290279,
        "cpi": 132.9008698099,
        "gdp_growth": 4.4401819631,
        "festival": 0.96749056076,
        "rainfall": 0.86510835587
      },
      {
        "date": "2024-06-03",
        "sales": 2991528.6415952104,
        "tv": 52812674.674728528,
        "youtube": 22771282.050700694,
        "facebook": 12879516.192904864,
        "instagram": 5842208.029430625,
        "print_media": 4498719.620392127,
        "radio": 45909727.732821167,
        "trade_spend": 13452399.764189012,
        "cpi": 133.2553842714,
        "gdp_growth": 4.1434289803,
        "festival": 0.96749056076,
        "rainfall": 4.433258495
      },
      {
        "date": "2024-06-10",
        "sales": 2550547.5190256936,
        "tv": 45448227.372363105,
        "youtube": 24733475.354639232,
        "facebook": 11985026.000115344,
        "instagram": 6145197.6709393812,
        "print_media": 4704459.4493441489,
        "radio": 48587348.833019726,
        "trade_spend": 6131477.4673698023,
        "cpi": 133.6233697467,
        "gdp_growth": 4.5199174183,
        "festival": 0.96749056076,
        "rainfall": 3.8336913922
      },
      {
        "date": "2024-06-17",
        "sales": 2046265.7753353699,
        "tv": 49470057.115282305,
        "youtube": 21973635.881324414,
        "facebook": 12217971.163913516,
        "instagram": 5616524.2926562354,
        "print_media": 4516282.6996378899,
        "radio": 43881419.714822665,
        "trade_spend": 1059961.9836001904,
        "cpi": 134.0016342173,
        "gdp_growth": 4.6418938596,
        "festival": 0.96749056076,
        "rainfall": 4.1833326551
      },
      {
        "date": "2024-06-24",
        "sales": 2821044.0216650181,
        "tv": 50672311.542126015,
        "youtube": 21871850.204152558,
        "facebook": 13124317.458108895,
        "instagram": 5686801.7866414012,
        "print_media": 4594198.280553394,
        "radio": 47980024.38066978,
        "trade_spend": 6449966.9497777205,
        "cpi": 134.3868357739,
        "gdp_growth": 4.6168524879,
        "festival": 0.96749056076,
        "rainfall": 4.2837821202
      },
      {
        "date": "2024-07-01",
        "sales": 2103220.1679820861,
        "tv": 51174767.584564835,
        "youtube": 24107376.732582211,
        "facebook": 12802506.647188609,
        "instagram": 6101726.0112353042,
        "print_media": 4494911.3539361674,
        "radio": 45961939.696418673,
        "trade_spend": 601134.6454185572,
        "cpi": 134.7755313488,
        "gdp_growth": 4.9272743539,
        "festival": 0.96749056076,
        "rainfall": 3.7671143757
      },
      {
        "date": "2024-07-08",
        "sales": 2175659.0573482784,
        "tv": 48836461.667778812,
        "youtube": 23131632.984390628,
        "facebook": 12475814.812829167,
        "instagram": 5873908.0781610422,
        "print_media": 4677163.0184498522,
        "radio": 45688625.209906638,
        "trade_spend": 992678.5525031186,
        "cpi": 135.1642269237,
        "gdp_growth": 5.215111289,
        "festival": 0.96749056076,
        "rainfall": 4.0304956569
      },
      {
        "date": "2024-07-15",
        "sales": 2272844.1952498578,
        "tv": 47103552.928126171,
        "youtube": 23865999.825817954,
        "facebook": 13764400.835867975,
        "instagram": 6149640.0487503884,
        "print_media": 4668989.5054772533,
        "radio": 50935125.098583423,
        "trade_spend": 838946.6836767381,
        "cpi": 135.5494284803,
        "gdp_growth": 5.7697158998,
        "festival": 0.96749056076,
        "rainfall": 3.0643827472
      },
      {
        "date": "2024-07-22",
        "sales": 2794377.2124554114,
        "tv": 48573656.948624402,
        "youtube": 22166314.197629597,
        "facebook": 11173088.583362745,
        "instagram": 5550571.6978621949,
        "print_media": 4696597.7542918222,
        "radio": 44337375.176272139,
        "trade_spend": 4634722.9106591586,
        "cpi": 135.9276929509,
        "gdp_growth": 5.3574696457,
        "festival": 0.96749056076,
        "rainfall": 3.737522212
      },
      {
        "date": "2024-07-29",
        "sales": 2391494.4233038486,
        "tv": 51389930.855628766,
        "youtube": 22719286.796494219,
        "facebook": 13011591.567926733,
        "instagram": 5845016.5160915181,
        "print_media": 4480674.832693805,
        "radio": 46155725.080512688,
        "trade_spend": 997908.1196759993,
        "cpi": 136.2956784262,
        "gdp_growth": 5.4617767627,
        "festival": 0.96749056076,
        "rainfall": 3.9718796102
      },
      {
        "date": "2024-08-05",
        "sales": 3233425.7656616573,
        "tv": 51072627.845615692,
        "youtube": 23263121.302226886,
        "facebook": 11953096.369278716,
        "instagram": 5847933.8973732488,
        "print_media": 4592313.4585160371,
        "radio": 45405720.286958307,
        "trade_spend": 5416338.2917624004,
        "cpi": 136.6501928877,
        "gdp_growth": 5.4184082923,
        "festival": 0.96749056076,
        "rainfall": 3.669689774
      },
      {
        "date": "2024-08-12",
        "sales": 2872957.2187641459,
        "tv": 51216055.086971566,
        "youtube": 22264353.524245325,
        "facebook": 13135687.328863148,
        "instagram": 5766439.4377353797,
        "print_media": 4261538.8436463326,
        "radio": 39483353.792132139,
        "trade_spend": 5861131.8713129926,
        "cpi": 136.9882407547,
        "gdp_growth": 4.8965349873,
        "festival": 0.96749056076,
        "rainfall": 4.5442399699
      },
      {
        "date": "2024-08-19",
        "sales": 2295600.5791021814,
        "tv": 47920076.051617205,
        "youtube": 26009409.807336595,
        "facebook": 11484170.868644062,
        "instagram": 6350299.0483317254,
        "print_media": 4756863.2548814518,
        "radio": 44379068.106620647,
        "trade_spend": 939402.6711529748,
        "cpi": 137.3070665666,
        "gdp_growth": 5.4614217407,
        "festival": 0.96749056076,
        "rainfall": 3.6143180285
      },
      {
        "date": "2024-08-26",
        "sales": 2019096.5953986829,
        "tv": 49432538.228970401,
        "youtube": 24025309.008742012,
        "facebook": 10568790.581126563,
        "instagram": 5861940.8598610591,
        "print_media": 5056992.5819672663,
        "radio": 47290994.128899544,
        "trade_spend": 730143.0929719516,
        "cpi": 137.6041951634,
        "gdp_growth": 5.4586125277,
        "festival": 0.96749056076,
        "rainfall": 3.9149537788
      },
      {
        "date": "2024-09-02",
        "sales": 3706569.8800519439,
        "tv": 149554300.91436091,
        "youtube": 23326880.217433918,
        "facebook": 37788591.147155978,
        "instagram": 8444235.1582023818,
        "print_media": 4500014.2326025544,
        "radio": 16798648.193439398,
        "trade_spend": 13607474.712204518,
        "cpi": 137.8774677795,
        "gdp_growth": 6.1202316195,
        "festival": 2.9024716823,
        "rainfall": 4.0882685296
      },
      {
        "date": "2024-09-09",
        "sales": 3436127.4063566015,
        "tv": 156564381.52274629,
        "youtube": 24770035.412218317,
        "facebook": 38491947.054692067,
        "instagram": 8803201.7879128698,
        "print_media": 4287888.1366660651,
        "radio": 14901488.776804844,
        "trade_spend": 11346025.486348506,
        "cpi": 138.1250735234,
        "gdp_growth": 5.2479291247,
        "festival": 2.9024716823,
        "rainfall": 4.486202296
      },
      {
        "date": "2024-09-16",
        "sales": 2576540.9238343141,
        "tv": 150360016.3383911,
        "youtube": 21502600.704896815,
        "facebook": 37691281.123106129,
        "instagram": 8069648.2532899762,
        "print_media": 4517420.8950708583,
        "radio": 14430499.933924561,
        "trade_spend": 718657.8534977053,
        "cpi": 138.3455757841,
        "gdp_growth": 5.2966611455,
        "festival": 2.9024716823,
        "rainfall": 3.6125809572
      },
      {
        "date": "2024-09-23",
        "sales": 2683540.251215647,
        "tv": 162458596.45549408,
        "youtube": 22592066.433227345,
        "facebook": 33993961.535648622,
        "instagram": 7917809.4402103312,
        "print_media": 4484582.1431595804,
        "radio": 16625789.999217283,
        "trade_spend": 1057367.4886064907,
        "cpi": 138.5379331806,
        "gdp_growth": 5.0841295296,
        "festival": 2.9024716823,
        "rainfall": 4.4017563493
      },
      {
        "date": "2024-09-30",
        "sales": 4088419.3380079661,
        "tv": 148821587.50277054,
        "youtube": 24701847.384437844,
        "facebook": 41111411.610304095,
        "instagram": 9051510.6379179787,
        "print_media": 4798185.2577008214,
        "radio": 13893287.196609575,
        "trade_spend": 12386409.307773354,
        "cpi": 138.7015147472,
        "gdp_growth": 4.6265422238,
        "festival": 2.9024716823,
        "rainfall": 4.051677295
      },
      {
        "date": "2024-10-07",
        "sales": 4258465.2600765517,
        "tv": 142162197.96204147,
        "youtube": 21301972.943897352,
        "facebook": 36910037.737049572,
        "instagram": 7951398.3624844272,
        "print_media": 13428768.764704494,
        "radio": 15457801.051602589,
        "trade_spend": 12977476.878853032,
        "cpi": 138.8361091349,
        "gdp_growth": 5.1975141391,
        "festival": 2.9024716823,
        "rainfall": 0.71411453171
      },
      {
        "date": "2024-10-14",
        "sales": 3267888.8046697481,
        "tv": 144037084.76133636,
        "youtube": 22294728.203653939,
        "facebook": 40736693.320543431,
        "instagram": 8532614.972785132,
        "print_media": 13989059.149320513,
        "radio": 14572076.564159641,
        "trade_spend": 806592.0486189931,
        "cpi": 138.9419276928,
        "gdp_growth": 4.9686738842,
        "festival": 2.9024716823,
        "rainfall": 1.1524568982
      },
      {
        "date": "2024-10-21",
        "sales": 3164302.1973377243,
        "tv": 141194076.83403081,
        "youtube": 26370080.123901613,
        "facebook": 37682095.78207992,
        "instagram": 9042225.6029883157,
        "print_media": 14278217.221460626,
        "radio": 15875230.279262139,
        "trade_spend": 1155857.5180248406,
        "cpi": 139.0196013864,
        "gdp_growth": 4.8816337794,
        "festival": 2.9024716823,
        "rainfall": 1.0725855599
      },
      {
        "date": "2024-10-28",
        "sales": 3405010.7881661318,
        "tv": 154777842.88719133,
        "youtube": 22715848.906200822,
        "facebook": 33336875.986901045,
        "instagram": 7876857.379930269,
        "print_media": 13855899.02005616,
        "radio": 15502344.160382474,
        "trade_spend": 5231995.1619860176,
        "cpi": 139.0701715968,
        "gdp_growth": 4.2944778098,
        "festival": 2.9024716823,
        "rainfall": 0.82989101735
      },
      {
        "date": "2024-11-04",
        "sales": 5149328.4959423235,
        "tv": 153515995.44256005,
        "youtube": 23118489.339895114,
        "facebook": 36596714.60240633,
        "instagram": 8283369.3282196559,
        "print_media": 13723260.921418022,
        "radio": 15261167.0240412,
        "trade_spend": 12457518.312182821,
        "cpi": 139.0950749349,
        "gdp_growth": 4.9289818048,
        "festival": 2.9024716823,
        "rainfall": 1.0333374226
      },
      {
        "date": "2024-11-11",
        "sales": 3287439.0535533167,
        "tv": 146864022.72709394,
        "youtube": 19805177.990501676,
        "facebook": 43637273.675343193,
        "instagram": 8324762.9656346552,
        "print_media": 13745735.13351717,
        "radio": 16135007.747169368,
        "trade_spend": 1019252.9283174493,
        "cpi": 139.0961222924,
        "gdp_growth": 4.0630195892,
        "festival": 2.9024716823,
        "rainfall": 0.89514484198
      },
      {
        "date": "2024-11-18",
        "sales": 3584484.7732178038,
        "tv": 161767956.26843482,
        "youtube": 21875158.510413449,
        "facebook": 31677857.341711819,
        "instagram": 7542817.4362538727,
        "print_media": 14062495.10332853,
        "radio": 15839948.583730608,
        "trade_spend": 5890548.3881511232,
        "cpi": 139.0754724349,
        "gdp_growth": 4.6566993549,
        "festival": 2.9024716823,
        "rainfall": 1.0466112448
      },
      {
        "date": "2024-11-25",
        "sales": 3771828.8596165874,
        "tv": 158844082.49707705,
        "youtube": 22981171.506610602,
        "facebook": 39965563.380673192,
        "instagram": 8592790.6393894404,
        "print_media": 13786219.205783837,
        "radio": 14394362.451076249,
        "trade_spend": 4571270.8451146185,
        "cpi": 139.0356005222,
        "gdp_growth": 5.1641186615,
        "festival": 2.9024716823,
        "rainfall": 1.2131937089
      },
      {
        "date": "2024-12-02",
        "sales": 3546645.2462928831,
        "tv": 47192666.712810442,
        "youtube": 72530072.629655451,
        "facebook": 12664867.074423635,
        "instagram": 15772501.233373456,
        "print_media": 4081597.7693156316,
        "radio": 14817749.162356643,
        "trade_spend": 13163114.868110729,
        "cpi": 138.979262015,
        "gdp_growth": 4.2702528163,
        "festival": 0.96749056076,
        "rainfall": 1.4937250446
      },
      {
        "date": "2024-12-09",
        "sales": 4796115.4917504378,
        "tv": 53438549.165336154,
        "youtube": 71842048.385530069,
        "facebook": 12513270.571608014,
        "instagram": 15619736.734266816,
        "print_media": 4449337.7074599816,
        "radio": 13791392.928788664,
        "trade_spend": 25603572.751129866,
        "cpi": 138.909452494,
        "gdp_growth": 4.476436485,
        "festival": 0.96749056076,
        "rainfall": 0.63628881368
      },
      {
        "date": "2024-12-16",
        "sales": 3057979.1438207203,
        "tv": 49866109.939319603,
        "youtube": 67026420.119453348,
        "facebook": 13097901.063529411,
        "instagram": 14715074.130243611,
        "print_media": 4817235.4260070613,
        "radio": 15012049.079952255,
        "trade_spend": 5494389.167868332,
        "cpi": 138.8293639778,
        "gdp_growth": 4.7739512819,
        "festival": 0.96749056076,
        "rainfall": 1.6598226608
      },
      {
        "date": "2024-12-23",
        "sales": 2647350.3795039761,
        "tv": 53656553.288336039,
        "youtube": 62267341.389802635,
        "facebook": 12485202.708782526,
        "instagram": 13701988.548838781,
        "print_media": 4782825.5607411023,
        "radio": 16038931.434575319,
        "trade_spend": 1115690.3402125186,
        "cpi": 138.7423383755,
        "gdp_growth": 4.7060523397,
        "festival": 0.96749056076,
        "rainfall": 0.41940520269
      },
      {
        "date": "2024-12-30",
        "sales": 2529616.8144860165,
        "tv": 50618524.730568647,
        "youtube": 68064054.635148972,
        "facebook": 13548165.3533551,
        "instagram": 14967627.462365305,
        "print_media": 4423686.7048832402,
        "radio": 15307795.134879151,
        "trade_spend": 948950.4986366718,
        "cpi": 138.6518187549,
        "gdp_growth": 4.5125099069,
        "festival": 0.96749056076,
        "rainfall": 0.96605408023
      },
      {
        "date": "2025-01-06",
        "sales": 3270921.2884533736,
        "tv": 48671480.050535046,
        "youtube": 23371770.024853956,
        "facebook": 39442529.966626525,
        "instagram": 8618607.0016334448,
        "print_media": 4893616.7001084844,
        "radio": 14426197.963503866,
        "trade_spend": 4073086.5068345862,
        "cpi": 138.5612991343,
        "gdp_growth": 5.1149596571,
        "festival": 1.9349811215,
        "rainfall": 1.1907807839
      },
      {
        "date": "2025-01-13",
        "sales": 2708323.272622087,
        "tv": 52288586.142650068,
        "youtube": 22094539.422845092,
        "facebook": 37326665.810676292,
        "instagram": 8151574.4656366473,
        "print_media": 4586972.4072388634,
        "radio": 14867847.812118931,
        "trade_spend": 778063.7805869348,
        "cpi": 138.474273532,
        "gdp_growth": 4.8895170542,
        "festival": 1.9349811215,
        "rainfall": 1.0974636706
      },
      {
        "date": "2025-01-20",
        "sales": 3470787.8040522747,
        "tv": 52386320.204450391,
        "youtube": 24341416.568436377,
        "facebook": 40613542.769709289,
        "instagram": 8929637.5906582046,
        "print_media": 4707285.4619129319,
        "radio": 15045000.624549383,
        "trade_spend": 4536694.4906881182,
        "cpi": 138.3941850157,
        "gdp_growth": 5.4467330842,
        "festival": 1.9349811215,
        "rainfall": 0.82306432574
      },
      {
        "date": "2025-01-27",
        "sales": 2946700.7782519376,
        "tv": 48704023.049147598,
        "youtube": 25169082.987678967,
        "facebook": 38145356.322192185,
        "instagram": 8848352.2297550123,
        "print_media": 4306211.9167384068,
        "radio": 14525769.678269722,
        "trade_spend": 1011105.2149297512,
        "cpi": 138.3243754947,
        "gdp_growth": 5.1104200203,
        "festival": 1.9349811215,
        "rainfall": 0.94894771104
      },
      {
        "date": "2025-02-03",
        "sales": 2795036.5906871068,
        "tv": 50010510.695262425,
        "youtube": 23744107.660163049,
        "facebook": 37388086.232415922,
        "instagram": 8487630.1552742012,
        "print_media": 4321934.0141307842,
        "radio": 15324719.134672748,
        "trade_spend": 1194576.2303446003,
        "cpi": 138.2680369875,
        "gdp_growth": 5.9033269693,
        "festival": 0.96749056076,
        "rainfall": 0.86244636178
      },
      {
        "date": "2025-02-10",
        "sales": 2752783.1176468963,
        "tv": 51951493.415960558,
        "youtube": 21917733.153415285,
        "facebook": 36374676.362665206,
        "instagram": 8021014.2669495782,
        "print_media": 4955418.9073234061,
        "radio": 15542673.838044245,
        "trade_spend": 1054407.4692108089,
        "cpi": 138.2281650748,
        "gdp_growth": 5.2355158539,
        "festival": 0.96749056076,
        "rainfall": 0.83318618506
      },
      {
        "date": "2025-02-17",
        "sales": 2819870.6630220711,
        "tv": 49669925.093982674,
        "youtube": 24425695.185268838,
        "facebook": 37356382.665167406,
        "instagram": 8620777.303570509,
        "print_media": 4494771.3402913185,
        "radio": 15723139.283258853,
        "trade_spend": 652545.936814019,
        "cpi": 138.2075152173,
        "gdp_growth": 5.3731932827,
        "festival": 0.96749056076,
        "rainfall": 1.2701180486
      },
      {
        "date": "2025-02-24",
        "sales": 3027755.7793060085,
        "tv": 48435093.936080597,
        "youtube": 22975218.241512779,
        "facebook": 39930868.313164614,
        "instagram": 8588130.4796190169,
        "print_media": 4536914.2532691229,
        "radio": 15700262.101804325,
        "trade_spend": 5663302.9291691417,
        "cpi": 138.2085625748,
        "gdp_growth": 5.6834877828,
        "festival": 0.96749056076,
        "rainfall": 1.1205476917
      },
      {
        "date": "2025-03-03",
        "sales": 2557436.8443195983,
        "tv": 49924640.733888134,
        "youtube": 68350893.13252078,
        "facebook": 10813347.498887705,
        "instagram": 14751513.376392925,
        "print_media": 4615614.3047610624,
        "radio": 16291605.81086769,
        "trade_spend": 746785.6005776258,
        "cpi": 138.2334659129,
        "gdp_growth": 5.0174472659,
        "festival": 0.96749056076,
        "rainfall": 0.80174554483
      },
      {
        "date": "2025-03-10",
        "sales": 2514671.5639566733,
        "tv": 48686208.907471009,
        "youtube": 67789785.755498201,
        "facebook": 11558765.406569324,
        "instagram": 14713833.691756574,
        "print_media": 4231858.9779063864,
        "radio": 14672950.209330434,
        "trade_spend": 861378.3130965652,
        "cpi": 138.2840361234,
        "gdp_growth": 5.3732562987,
        "festival": 0.96749056076,
        "rainfall": 1.2852995119
      },
      {
        "date": "2025-03-17",
        "sales": 2747493.6840743884,
        "tv": 52866661.704322867,
        "youtube": 60883803.839312382,
        "facebook": 11224269.140358919,
        "instagram": 13299187.681898369,
        "print_media": 4718833.4040902536,
        "radio": 13978744.991531357,
        "trade_spend": 979718.468735154,
        "cpi": 138.361709817,
        "gdp_growth": 5.5968568512,
        "festival": 0.96749056076,
        "rainfall": 1.1054517989
      },
      {
        "date": "2025-03-24",
        "sales": 2634868.5131177274,
        "tv": 49052226.42014128,
        "youtube": 72028138.884249568,
        "facebook": 11847064.178647403,
        "instagram": 15590334.194714656,
        "print_media": 4655596.8725021575,
        "radio": 15267040.40976928,
        "trade_spend": 1305433.0066709218,
        "cpi": 138.4675283748,
        "gdp_growth": 4.6146174036,
        "festival": 0.96749056076,
        "rainfall": 1.2589622203
      },
      {
        "date": "2025-03-31",
        "sales": 2779304.2858608081,
        "tv": 52454850.241178781,
        "youtube": 75029571.375533536,
        "facebook": 12890809.173266618,
        "instagram": 16294995.19243337,
        "print_media": 4593807.5538338376,
        "radio": 15081001.260036848,
        "trade_spend": 1513358.8581622709,
        "cpi": 138.6021227625,
        "gdp_growth": 5.0305401089,
        "festival": 0.96749056076,
        "rainfall": 1.2033247628
      },
      {
        "date": "2025-04-07",
        "sales": 2973195.544414233,
        "tv": 44665610.417016268,
        "youtube": 80804484.843369678,
        "facebook": 14790545.38612617,
        "instagram": 17639951.507286552,
        "print_media": 4535003.3186136875,
        "radio": 15934483.337516164,
        "trade_spend": 1046247.7456722808,
        "cpi": 138.7657043291,
        "gdp_growth": 4.9339341751,
        "festival": 0.96749056076,
        "rainfall": 0.76042419396
      },
      {
        "date": "2025-04-14",
        "sales": 2887386.1252641203,
        "tv": 48355033.905854255,
        "youtube": 66598358.59523347,
        "facebook": 12625669.57179107,
        "instagram": 14582238.676225802,
        "print_media": 4457958.2493786924,
        "radio": 13718641.224217419,
        "trade_spend": 898844.0530870185,
        "cpi": 138.9580617256,
        "gdp_growth": 4.9775967584,
        "festival": 0.96749056076,
        "rainfall": 0.84204760929
      },
      {
        "date": "2025-04-21",
        "sales": 3509957.2352832304,
        "tv": 50074604.525645405,
        "youtube": 73247398.480758518,
        "facebook": 12731027.073422784,
        "instagram": 15922582.403493982,
        "print_media": 4338906.2822496593,
        "radio": 17158893.043685548,
        "trade_spend": 4864631.9808692187,
        "cpi": 139.1785639863,
        "gdp_growth": 4.2762295801,
        "festival": 0.96749056076,
        "rainfall": 1.239052816
      },
      {
        "date": "2025-04-28",
        "sales": 3032792.8737769295,
        "tv": 50920831.954550788,
        "youtube": 65900592.111823417,
        "facebook": 13430018.072475912,
        "instagram": 14523120.229612276,
        "print_media": 4593619.8178473748,
        "radio": 14966842.910924792,
        "trade_spend": 1098671.3899802864,
        "cpi": 139.4261697302,
        "gdp_growth": 4.1717632523,
        "festival": 0.96749056076,
        "rainfall": 1.1974770355
      },
      {
        "date": "2025-05-05",
        "sales": 3763293.116580341,
        "tv": 50385341.637189187,
        "youtube": 67022001.86545828,
        "facebook": 12624543.871164102,
        "instagram": 14666854.760208068,
        "print_media": 4825601.3802124802,
        "radio": 14794288.077974675,
        "trade_spend": 6071018.0758957798,
        "cpi": 139.6994423464,
        "gdp_growth": 4.6660249452,
        "festival": 0.96749056076,
        "rainfall": 1.0057959074
      },
      {
        "date": "2025-05-12",
        "sales": 3895544.3764804262,
        "tv": 51560432.179549135,
        "youtube": 67160600.459510759,
        "facebook": 13769579.356154991,
        "instagram": 14809078.027517652,
        "print_media": 4778374.9876412665,
        "radio": 14743293.54419386,
        "trade_spend": 6293020.6476970743,
        "cpi": 139.9965709432,
        "gdp_growth": 4.5701650939,
        "festival": 0.96749056076,
        "rainfall": 1.0477681352
      },
      {
        "date": "2025-05-19",
        "sales": 3132769.0588759459,
        "tv": 50047752.315991767,
        "youtube": 74111960.565492839,
        "facebook": 13118062.619312404,
        "instagram": 16134198.375029808,
        "print_media": 4657376.9070193516,
        "radio": 15803603.582270319,
        "trade_spend": 5756162.7375339391,
        "cpi": 140.315396755,
        "gdp_growth": 4.5562861069,
        "festival": 0.96749056076,
        "rainfall": 1.4000962172
      },
      {
        "date": "2025-05-26",
        "sales": 3507482.2979457662,
        "tv": 53257864.060121536,
        "youtube": 72878670.344028309,
        "facebook": 13036411.206617964,
        "instagram": 15879375.189467458,
        "print_media": 4346936.7106387541,
        "radio": 15780650.216338929,
        "trade_spend": 6716971.0133861545,
        "cpi": 140.653444622,
        "gdp_growth": 4.6136357326,
        "festival": 0.96749056076,
        "rainfall": 0.83251615727
      },
      {
        "date": "2025-06-02",
        "sales": 3111086.5692329486,
        "tv": 50653861.908122316,
        "youtube": 22893087.914374456,
        "facebook": 12800878.2657605,
        "instagram": 5858705.4094509408,
        "print_media": 4560745.8767738119,
        "radio": 43652400.649684213,
        "trade_spend": 6395129.431873057,
        "cpi": 141.0079590835,
        "gdp_growth": 4.3629483963,
        "festival": 0.96749056076,
        "rainfall": 4.2146922576
      },
      {
        "date": "2025-06-09",
        "sales": 2665784.5092951613,
        "tv": 50013257.361447483,
        "youtube": 23746866.885102309,
        "facebook": 11858283.36106175,
        "instagram": 5935201.713126637,
        "print_media": 4656538.7125718752,
        "radio": 42164126.982659869,
        "trade_spend": 1011700.1873454974,
        "cpi": 141.3759445588,
        "gdp_growth": 4.714824316,
        "festival": 0.96749056076,
        "rainfall": 3.9871757656
      },
      {
        "date": "2025-06-16",
        "sales": 3191389.9021409326,
        "tv": 51694354.157042749,
        "youtube": 23221432.978982314,
        "facebook": 13778372.946696751,
        "instagram": 6022123.8904661387,
        "print_media": 4817006.2091278695,
        "radio": 43775332.764994219,
        "trade_spend": 6040070.0913257403,
        "cpi": 141.7542090294,
        "gdp_growth": 4.8316923827,
        "festival": 0.96749056076,
        "rainfall": 3.9824727793
      },
      {
        "date": "2025-06-23",
        "sales": 3357677.1606239155,
        "tv": 51761377.14868132,
        "youtube": 25907731.106827311,
        "facebook": 11118156.747924186,
        "instagram": 6293361.8961578812,
        "print_media": 4365166.0848927442,
        "radio": 43388224.441792801,
        "trade_spend": 11801606.970977597,
        "cpi": 142.139410586,
        "gdp_growth": 4.643100582,
        "festival": 0.96749056076,
        "rainfall": 4.3822057334
      }
    ]
  }
}
